{
  "address": "0x66442B0C5260B92cAa9c234ECf2408CBf6b19a6f",
  "kind": "pool_implementation",
  "written_at": "2026-06-17T02:11:09Z",
  "abi_status": "source_getsourcecode",
  "abi_source": "etherscan_getsourcecode",
  "source_status": "verified",
  "source_source": "etherscan_getsourcecode",
  "source_files": [
    "source/CurveTricryptoOptimizedWETH.vy"
  ],
  "source_file_count": 1,
  "etherscan_source_metadata": {
    "ContractName": "CurveTricryptoOptimizedWETH",
    "CompilerVersion": "vyper:0.3.9",
    "OptimizationUsed": "1",
    "Runs": "1",
    "ConstructorArguments": "",
    "EVMVersion": "shanghai",
    "Library": "",
    "LicenseType": "None",
    "Proxy": "0",
    "Implementation": "",
    "SwarmSource": ""
  },
  "used_by_pool_count": 121,
  "first_seen_pool": "0x7F86Bf177Dd4F3494b841a37e810A34dD56c829B",
  "first_seen_factory": "0x0c0e5f2fF0ff18a3be9b835635039256dC4B4963",
  "first_seen_block": 17371455,
  "example_pools": [
    "0x7F86Bf177Dd4F3494b841a37e810A34dD56c829B",
    "0xf5f5B97624542D72A9E06f04804Bf81baA15e2B4",
    "0x2889302a794dA87fBF1D6Db415C1492194663D13",
    "0x5426178799ee0a0181A89b4f57eFddfAb49941Ec",
    "0x4eBdF703948ddCEA3B11f675B4D1Fba9d2414A14"
  ],
  "state_manifest": {
    "constants": {
      "N_COINS": 3,
      "PRECISION": "1000000000000000000"
    },
    "calls": [
      {
        "name": "A",
        "address_ref": "pool_address",
        "signature": "A()",
        "selector": "f446c1d0",
        "inputs": [],
        "arg_policy": "none",
        "outputs": [
          "uint256"
        ]
      },
      {
        "name": "ADMIN_FEE",
        "address_ref": "pool_address",
        "signature": "ADMIN_FEE()",
        "selector": "4469ed14",
        "inputs": [],
        "arg_policy": "none",
        "outputs": [
          "uint256"
        ]
      },
      {
        "name": "D",
        "address_ref": "pool_address",
        "signature": "D()",
        "selector": "0f529ba2",
        "inputs": [],
        "arg_policy": "none",
        "outputs": [
          "uint256"
        ]
      },
      {
        "name": "DOMAIN_SEPARATOR",
        "address_ref": "pool_address",
        "signature": "DOMAIN_SEPARATOR()",
        "selector": "3644e515",
        "inputs": [],
        "arg_policy": "none",
        "outputs": [
          "bytes32"
        ]
      },
      {
        "name": "MATH",
        "address_ref": "pool_address",
        "signature": "MATH()",
        "selector": "ed6c1546",
        "inputs": [],
        "arg_policy": "none",
        "outputs": [
          "address"
        ]
      },
      {
        "name": "WETH20",
        "address_ref": "pool_address",
        "signature": "WETH20()",
        "selector": "17e26cd1",
        "inputs": [],
        "arg_policy": "none",
        "outputs": [
          "address"
        ]
      },
      {
        "name": "adjustment_step",
        "address_ref": "pool_address",
        "signature": "adjustment_step()",
        "selector": "083812e5",
        "inputs": [],
        "arg_policy": "none",
        "outputs": [
          "uint256"
        ]
      },
      {
        "name": "admin_actions_deadline",
        "address_ref": "pool_address",
        "signature": "admin_actions_deadline()",
        "selector": "405e28f8",
        "inputs": [],
        "arg_policy": "none",
        "outputs": [
          "uint256"
        ]
      },
      {
        "name": "allowed_extra_profit",
        "address_ref": "pool_address",
        "signature": "allowed_extra_profit()",
        "selector": "49fe9e77",
        "inputs": [],
        "arg_policy": "none",
        "outputs": [
          "uint256"
        ]
      },
      {
        "name": "balances",
        "address_ref": "pool_address",
        "signature": "balances(uint256)",
        "selector": "4903b0d1",
        "inputs": [
          "uint256"
        ],
        "arg_policy": "range:n_coins",
        "outputs": [
          "uint256"
        ]
      },
      {
        "name": "coins",
        "address_ref": "pool_address",
        "signature": "coins(uint256)",
        "selector": "c6610657",
        "inputs": [
          "uint256"
        ],
        "arg_policy": "range:n_coins",
        "outputs": [
          "address"
        ]
      },
      {
        "name": "decimals",
        "address_ref": "pool_address",
        "signature": "decimals()",
        "selector": "313ce567",
        "inputs": [],
        "arg_policy": "none",
        "outputs": [
          "uint8"
        ]
      },
      {
        "name": "factory",
        "address_ref": "pool_address",
        "signature": "factory()",
        "selector": "c45a0155",
        "inputs": [],
        "arg_policy": "none",
        "outputs": [
          "address"
        ]
      },
      {
        "name": "fee",
        "address_ref": "pool_address",
        "signature": "fee()",
        "selector": "ddca3f43",
        "inputs": [],
        "arg_policy": "none",
        "outputs": [
          "uint256"
        ]
      },
      {
        "name": "fee_gamma",
        "address_ref": "pool_address",
        "signature": "fee_gamma()",
        "selector": "72d4f0e2",
        "inputs": [],
        "arg_policy": "none",
        "outputs": [
          "uint256"
        ]
      },
      {
        "name": "fee_receiver",
        "address_ref": "pool_address",
        "signature": "fee_receiver()",
        "selector": "cab4d3db",
        "inputs": [],
        "arg_policy": "none",
        "outputs": [
          "address"
        ]
      },
      {
        "name": "future_A_gamma",
        "address_ref": "pool_address",
        "signature": "future_A_gamma()",
        "selector": "f30cfad5",
        "inputs": [],
        "arg_policy": "none",
        "outputs": [
          "uint256"
        ]
      },
      {
        "name": "future_A_gamma_time",
        "address_ref": "pool_address",
        "signature": "future_A_gamma_time()",
        "selector": "f9ed9597",
        "inputs": [],
        "arg_policy": "none",
        "outputs": [
          "uint256"
        ]
      },
      {
        "name": "gamma",
        "address_ref": "pool_address",
        "signature": "gamma()",
        "selector": "b1373929",
        "inputs": [],
        "arg_policy": "none",
        "outputs": [
          "uint256"
        ]
      },
      {
        "name": "get_virtual_price",
        "address_ref": "pool_address",
        "signature": "get_virtual_price()",
        "selector": "bb7b8b80",
        "inputs": [],
        "arg_policy": "none",
        "outputs": [
          "uint256"
        ]
      },
      {
        "name": "initial_A_gamma",
        "address_ref": "pool_address",
        "signature": "initial_A_gamma()",
        "selector": "204fe3d5",
        "inputs": [],
        "arg_policy": "none",
        "outputs": [
          "uint256"
        ]
      },
      {
        "name": "initial_A_gamma_time",
        "address_ref": "pool_address",
        "signature": "initial_A_gamma_time()",
        "selector": "e89876ff",
        "inputs": [],
        "arg_policy": "none",
        "outputs": [
          "uint256"
        ]
      },
      {
        "name": "last_prices",
        "address_ref": "pool_address",
        "signature": "last_prices(uint256)",
        "selector": "59189017",
        "inputs": [
          "uint256"
        ],
        "arg_policy": "range:n_coins_minus_1",
        "outputs": [
          "uint256"
        ]
      },
      {
        "name": "last_prices_timestamp",
        "address_ref": "pool_address",
        "signature": "last_prices_timestamp()",
        "selector": "6112c747",
        "inputs": [],
        "arg_policy": "none",
        "outputs": [
          "uint256"
        ]
      },
      {
        "name": "lp_price",
        "address_ref": "pool_address",
        "signature": "lp_price()",
        "selector": "54f0f7d5",
        "inputs": [],
        "arg_policy": "none",
        "outputs": [
          "uint256"
        ]
      },
      {
        "name": "ma_time",
        "address_ref": "pool_address",
        "signature": "ma_time()",
        "selector": "09c3da6a",
        "inputs": [],
        "arg_policy": "none",
        "outputs": [
          "uint256"
        ]
      },
      {
        "name": "mid_fee",
        "address_ref": "pool_address",
        "signature": "mid_fee()",
        "selector": "92526c0c",
        "inputs": [],
        "arg_policy": "none",
        "outputs": [
          "uint256"
        ]
      },
      {
        "name": "name",
        "address_ref": "pool_address",
        "signature": "name()",
        "selector": "06fdde03",
        "inputs": [],
        "arg_policy": "none",
        "outputs": [
          "string"
        ]
      },
      {
        "name": "out_fee",
        "address_ref": "pool_address",
        "signature": "out_fee()",
        "selector": "ee8de675",
        "inputs": [],
        "arg_policy": "none",
        "outputs": [
          "uint256"
        ]
      },
      {
        "name": "packed_fee_params",
        "address_ref": "pool_address",
        "signature": "packed_fee_params()",
        "selector": "e3616405",
        "inputs": [],
        "arg_policy": "none",
        "outputs": [
          "uint256"
        ]
      },
      {
        "name": "packed_rebalancing_params",
        "address_ref": "pool_address",
        "signature": "packed_rebalancing_params()",
        "selector": "3dd65478",
        "inputs": [],
        "arg_policy": "none",
        "outputs": [
          "uint256"
        ]
      },
      {
        "name": "precisions",
        "address_ref": "pool_address",
        "signature": "precisions()",
        "selector": "3620604b",
        "inputs": [],
        "arg_policy": "none",
        "outputs": [
          "uint256[3]"
        ]
      },
      {
        "name": "price_oracle",
        "address_ref": "pool_address",
        "signature": "price_oracle(uint256)",
        "selector": "68727653",
        "inputs": [
          "uint256"
        ],
        "arg_policy": "range:n_coins_minus_1",
        "outputs": [
          "uint256"
        ]
      },
      {
        "name": "price_scale",
        "address_ref": "pool_address",
        "signature": "price_scale(uint256)",
        "selector": "a3f7cdd5",
        "inputs": [
          "uint256"
        ],
        "arg_policy": "range:n_coins_minus_1",
        "outputs": [
          "uint256"
        ]
      },
      {
        "name": "salt",
        "address_ref": "pool_address",
        "signature": "salt()",
        "selector": "bfa0b133",
        "inputs": [],
        "arg_policy": "none",
        "outputs": [
          "bytes32"
        ]
      },
      {
        "name": "symbol",
        "address_ref": "pool_address",
        "signature": "symbol()",
        "selector": "95d89b41",
        "inputs": [],
        "arg_policy": "none",
        "outputs": [
          "string"
        ]
      },
      {
        "name": "totalSupply",
        "address_ref": "pool_address",
        "signature": "totalSupply()",
        "selector": "18160ddd",
        "inputs": [],
        "arg_policy": "none",
        "outputs": [
          "uint256"
        ]
      },
      {
        "name": "version",
        "address_ref": "pool_address",
        "signature": "version()",
        "selector": "54fd4d50",
        "inputs": [],
        "arg_policy": "none",
        "outputs": [
          "string"
        ]
      },
      {
        "name": "virtual_price",
        "address_ref": "pool_address",
        "signature": "virtual_price()",
        "selector": "0c46b72a",
        "inputs": [],
        "arg_policy": "none",
        "outputs": [
          "uint256"
        ]
      },
      {
        "name": "xcp_profit",
        "address_ref": "pool_address",
        "signature": "xcp_profit()",
        "selector": "7ba1a74d",
        "inputs": [],
        "arg_policy": "none",
        "outputs": [
          "uint256"
        ]
      },
      {
        "name": "xcp_profit_a",
        "address_ref": "pool_address",
        "signature": "xcp_profit_a()",
        "selector": "0b7b594b",
        "inputs": [],
        "arg_policy": "none",
        "outputs": [
          "uint256"
        ]
      }
    ],
    "simulated_functions": [
      {
        "name": "calc_token_amount",
        "signature": "calc_token_amount(uint256[3],bool)",
        "selector": "3883e119",
        "inputs": [
          "uint256[3]",
          "bool"
        ],
        "outputs": [
          "uint256"
        ]
      },
      {
        "name": "calc_token_fee",
        "signature": "calc_token_fee(uint256[3],uint256[3])",
        "selector": "cde699fa",
        "inputs": [
          "uint256[3]",
          "uint256[3]"
        ],
        "outputs": [
          "uint256"
        ]
      },
      {
        "name": "calc_withdraw_one_coin",
        "signature": "calc_withdraw_one_coin(uint256,uint256)",
        "selector": "4fb08c5e",
        "inputs": [
          "uint256",
          "uint256"
        ],
        "outputs": [
          "uint256"
        ]
      },
      {
        "name": "fee_calc",
        "signature": "fee_calc(uint256[3])",
        "selector": "572e5625",
        "inputs": [
          "uint256[3]"
        ],
        "outputs": [
          "uint256"
        ]
      },
      {
        "name": "get_dx",
        "signature": "get_dx(uint256,uint256,uint256)",
        "selector": "37ed3a7a",
        "inputs": [
          "uint256",
          "uint256",
          "uint256"
        ],
        "outputs": [
          "uint256"
        ]
      },
      {
        "name": "get_dy",
        "signature": "get_dy(uint256,uint256,uint256)",
        "selector": "556d6e9f",
        "inputs": [
          "uint256",
          "uint256",
          "uint256"
        ],
        "outputs": [
          "uint256"
        ]
      }
    ]
  }
}
